zipbomb/__init__.py
zipbomb/__main__.py
zipbomb-1.0.3.dist-info/LICENSE
zipbomb-1.0.3.dist-info/METADATA
zipbomb-1.0.3.dist-info/WHEEL
zipbomb-1.0.3.dist-info/entry_points.txt
zipbomb-1.0.3.dist-info/top_level.txt
zipbomb-1.0.3.dist-info/RECORD
