Metadata-Version: 2.1
Name: zipbomb
Version: 1.0.3
Summary: Create zipbombs using python
Home-page: https://github.com/donno2048/zipbomb
Author: Elisha Hollander
Author-email: just4now666666@gmail.com
License: MIT
Project-URL: Documentation, https://github.com/donno2048/zipbomb#readme
Project-URL: Bug Reports, https://github.com/donno2048/zipbomb/issues
Project-URL: Source Code, https://github.com/donno2048/zipbomb
Platform: UNKNOWN
Classifier: Programming Language :: Python :: 3
Requires-Python: >=3.0
License-File: LICENSE
